ShortDiff/__init__.py
ShortDiff/__main__.py
ShortDiff/test.py
ShortDiff-0.1.3.dist-info/LICENSE
ShortDiff-0.1.3.dist-info/METADATA
ShortDiff-0.1.3.dist-info/WHEEL
ShortDiff-0.1.3.dist-info/top_level.txt
ShortDiff-0.1.3.dist-info/RECORD
