Metadata-Version: 2.1
Name: ShortDiff
Version: 0.1.3
Summary: A simple one way diff tool
Home-page: https://github.com/Lattay/ShortDiff
Author: Theo (Lattay) Cavignac
Author-email: theo.cavignac@gmail.com
License: UNKNOWN
Platform: UNKNOWN
Classifier: Programming Language :: Python :: 3
Classifier: License :: OSI Approved :: MIT License
Classifier: Operating System :: OS Independent
Classifier: Intended Audience :: Information Technology
